<system>
	<name>HAT-P-5</name>
	<rightascension>18h17m37.31s</rightascension>
	<declination>+36d37m17.1s</declination>
	<distance errorminus="30.00" errorplus="30.00">340.00</distance>
	<star>
		<spectraltype>G</spectraltype>
		<mass errorminus="0.06" errorplus="0.06">1.16</mass>
		<radius errorminus="0.05" errorplus="0.05">1.17</radius>
		<magV errorminus="0.16" errorplus="0.16">11.95</magV>
		<magR>12.0</magR>
		<magB errorminus="0.30" errorplus="0.30">12.92</magB>
		<magJ errorminus="0.021" errorplus="0.021">10.844</magJ>
		<magH errorminus="0.021" errorplus="0.021">10.522</magH>
		<magK errorminus="0.018" errorplus="0.018">10.481</magK>
		<metallicity>0.24</metallicity>
		<name>HAT-P-5</name>
		<temperature errorminus="100.00" errorplus="100.00">5960.00</temperature>
		<planet>
			<name>HAT-P-5 b</name>
			<name>2MASS J18173731+3637170 b</name>
			<name>TYC 2634-01087-1 b</name>
			<list>Confirmed planets</list>
			<mass errorminus="0.11000" errorplus="0.11000">1.06000</mass>
			<radius errorminus="0.050" errorplus="0.050">1.260</radius>
			<period errorminus="0.00002500" errorplus="0.00002500">2.78849100</period>
			<semimajoraxis errorminus="0.000760" errorplus="0.000760">0.040750</semimajoraxis>
			<eccentricity>0.000000</eccentricity>
			<inclination errorminus="0.440" errorplus="0.440">86.750</inclination>
			<transittime errorminus="0.00022" errorplus="0.00022" unit="BJD">2454241.77663</transittime>
			<discoverymethod>transit</discoverymethod>
			<lastupdate>14/05/14</lastupdate>
			<discoveryyear>2007</discoveryyear>
			<temperature>1387.4</temperature>
			<istransiting>1</istransiting>
		</planet>
	</star>
</system>
