<system>
	<name>HD 16175</name>
	<rightascension>2 36 61.9999920</rightascension>
	<declination>42 3 45.0</declination>
	<distance>59.8</distance>
	<star>
		<mass errorminus="0.09" errorplus="0.09">1.35</mass>
		<radius errorminus="0.04" errorplus="0.04">1.87</radius>
		<magV>7.28</magV>
		<magB errorminus="0.01" errorplus="0.01">7.92</magB>
		<magJ>6.17</magJ>
		<magH>5.92</magH>
		<magK>5.85</magK>
		<metallicity errorminus="0.03" errorplus="0.03">0.37</metallicity>
		<spectraltype>G0</spectraltype>
		<name>HD 16175</name>
		<temperature errorminus="34.0" errorplus="34.0">6022.0</temperature>
		<age errorminus="1.0" errorplus="1.0">5.3</age>
		<planet>
			<name>HD 16175 b</name>
			<list>Confirmed planets</list>
			<mass errorminus="0.37000" errorplus="0.37000">4.77000</mass>
			<period errorminus="2.80000000" errorplus="2.80000000">995.40000000</period>
			<semimajoraxis errorminus="0.076000" errorplus="0.076000">2.148000</semimajoraxis>
			<eccentricity errorminus="0.020000" errorplus="0.020000">0.637000</eccentricity>
			<discoverymethod>RV</discoverymethod>
			<lastupdate>16/05/19</lastupdate>
			<discoveryyear>2007</discoveryyear>
			<temperature>243.7</temperature>
		</planet>
	</star>
</system>
