<system>
	<name>Kepler-913</name>
	<rightascension>19 48 139.949280</rightascension>
	<declination>41 57 8.75160000</declination>
	<distance>597.0</distance>
	<star>
		<name>Kepler-913</name>
		<temperature errorminus="30.74" errorplus="34.09">4687.0</temperature>
		<mass errorminus="0.01" errorplus="0.01">0.63</mass>
		<radius errorminus="0.01" errorplus="0.01">0.61</radius>
		<metallicity errorminus="0.055" errorplus="0.026">-0.52</metallicity>
		<magK>13.477</magK>
		<magH>13.523</magH>
		<magJ>14.361</magJ>
		<planet>
			<name>Kepler-913 b</name>
			<discoverymethod>transit</discoverymethod>
			<list>Confirmed planets</list>
			<discoveryyear>2016</discoveryyear>
			<lastupdate>16/05/12</lastupdate>
			<istransiting>1</istransiting>
			<new>1</new>
			<description>This planet was discovered by the NASA Kepler spacecraft and is part of the May 10th 2016 data release. Although not many details are known about this particular system yet, it has a very low probability of being a false positive.</description>
			<period errorminus="3.426e-05" errorplus="3.426e-05">10.29672521</period>
			<radius errorminus="0.005" errorplus="0.007">0.184</radius>
		</planet>
	</star>
</system>
