<system>
	<name>Kepler-280</name>
	<name>KOI-1240</name>
	<name>KIC 6690082</name>
	<rightascension>19 23 153.720707</rightascension>
	<declination>42 10 50.1167999</declination>
	<distance>771.80</distance>
	<star>
		<magJ errorminus="0.023" errorplus="0.023">13.289</magJ>
		<magH errorminus="0.024" errorplus="0.024">12.914</magH>
		<magK errorminus="0.022" errorplus="0.022">12.844</magK>
		<name>Kepler-280</name>
		<name>KOI-1240</name>
		<name>KIC 6690082</name>
		<temperature errorminus="200" errorplus="200">5744</temperature>
		<radius errorminus="0.43" errorplus="0.43">0.89</radius>
		<mass>0.91</mass>
		<metallicity>-0.169</metallicity>
		<planet>
			<name>Kepler-280 b</name>
			<name>KOI-1240 b</name>
			<name>KOI-1240.01</name>
			<name>KIC 6690082 b</name>
			<name>KIC 6690082.01</name>
			<radius errorminus="0.062" errorplus="0.062">0.129</radius>
			<period errorminus="0.00000600" errorplus="0.00000600">2.13954200</period>
			<transittime errorminus="0.0015000" errorplus="0.0015000">2454966.6526000</transittime>
			<list>Confirmed planets</list>
			<description>Kepler-280 b has been discovered by the Kepler spacecraft and was originally classified as a planet candidate. A new statistical analysis led by a team at NASA Ames Research Center has validated the planet with more than 99 percent confidence. Although many parameters of Kepler-280 b are still unknown, the object is highly unlikely to be a false positive.</description>
			<discoveryyear>2014</discoveryyear>
			<lastupdate>14/05/14</lastupdate>
			<discoverymethod>transit</discoverymethod>
			<istransiting>1</istransiting>
			<semimajoraxis>0.032000</semimajoraxis>
		</planet>
		<planet>
			<name>Kepler-280 c</name>
			<name>KOI-1240 c</name>
			<name>KOI-1240.02</name>
			<name>KIC 6690082 c</name>
			<name>KIC 6690082.02</name>
			<radius errorminus="0.087" errorplus="0.087">0.179</radius>
			<period errorminus="0.00000900" errorplus="0.00000900">4.80709100</period>
			<transittime errorminus="0.0010400" errorplus="0.0010400">2454967.6424900</transittime>
			<list>Confirmed planets</list>
			<description>Kepler-280 c has been discovered by the Kepler spacecraft and was originally classified as a planet candidate. A new statistical analysis led by a team at NASA Ames Research Center has validated the planet with more than 99 percent confidence. Although many parameters of Kepler-280 c are still unknown, the object is highly unlikely to be a false positive.</description>
			<discoveryyear>2014</discoveryyear>
			<lastupdate>14/05/14</lastupdate>
			<discoverymethod>transit</discoverymethod>
			<istransiting>1</istransiting>
			<semimajoraxis>0.056000</semimajoraxis>
		</planet>
	</star>
</system>
